{
  "type": "flex",
  "altText": "寵物認養查詢結果",
  "contents": {
    "type": "carousel",
    "contents": [
      {
        "type": "bubble",
        "hero": {
          "type": "image",
          "url": "",
          "size": "full",
          "aspectRatio": "20:13",
          "aspectMode": "cover"
        },
        "body": {
          "type": "box",
          "layout": "vertical",
          "contents": [
            {
              "type": "text",
              "text": "混種犬  白色 性別:母",
              "weight": "bold",
              "size": "xl"
            },
            {
              "type": "box",
              "layout": "baseline",
              "margin": "md",
              "contents": [
                {
                  "type": "text",
                  "text": "4.0",
                  "size": "sm",
                  "color": "#999999",
                  "margin": "md",
                  "flex": 0
                }
              ]
            },
            {
              "type": "box",
              "layout": "vertical",
              "margin": "lg",
              "spacing": "sm",
              "contents": [
                {
                  "type": "box",
                  "layout": "baseline",
                  "spacing": "sm",
                  "contents": [
                    {
                      "type": "text",
                      "text": "Place",
                      "color": "#aaaaaa",
                      "size": "sm",
                      "flex": 1
                    },
                    {
                      "type": "text",
                      "text": "Flex Tower, 7-7-4 Midori-ku, Tokyo",
                      "wrap": true,
                      "color": "#666666",
                      "size": "sm",
                      "flex": 5
                    }
                  ]
                },
                {
                  "type": "box",
                  "layout": "baseline",
                  "spacing": "sm",
                  "contents": [
                    {
                      "type": "text",
                      "text": "Time",
                      "color": "#aaaaaa",
                      "size": "sm",
                      "flex": 1
                    },
                    {
                      "type": "text",
                      "text": "10:00 - 23:00",
                      "wrap": true,
                      "color": "#666666",
                      "size": "sm",
                      "flex": 5
                    }
                  ]
                }
              ]
            }
          ]
        },
        "footer": {
          "type": "box",
          "layout": "vertical",
          "spacing": "sm",
          "contents": [
            {
              "type": "button",
              "style": "link",
              "height": "sm",
              "action": {
                "type": "uri",
                "label": "CALL",
                "uri": "https://line.me/"
              }
            },
            {
              "type": "button",
              "style": "link",
              "height": "sm",
              "action": {
                "type": "uri",
                "label": "WEBSITE",
                "uri": "https://line.me/"
              }
            },
            {
              "type": "box",
              "layout": "vertical",
              "contents": [],
              "margin": "sm"
            }
          ],
          "flex": 0
        }
      },
      {
        "type": "bubble",
        "hero": {
          "type": "image",
          "url": "",
          "size": "full",
          "aspectRatio": "20:13",
          "aspectMode": "cover"
        },
        "body": {
          "type": "box",
          "layout": "vertical",
          "contents": [
            {
              "type": "text",
              "text": "混種犬  黑色 性別:母",
              "weight": "bold",
              "size": "xl"
            },
            {
              "type": "box",
              "layout": "baseline",
              "margin": "md",
              "contents": [
                {
                  "type": "text",
                  "text": "4.0",
                  "size": "sm",
                  "color": "#999999",
                  "margin": "md",
                  "flex": 0
                }
              ]
            },
            {
              "type": "box",
              "layout": "vertical",
              "margin": "lg",
              "spacing": "sm",
              "contents": [
                {
                  "type": "box",
                  "layout": "baseline",
                  "spacing": "sm",
                  "contents": [
                    {
                      "type": "text",
                      "text": "Place",
                      "color": "#aaaaaa",
                      "size": "sm",
                      "flex": 1
                    },
                    {
                      "type": "text",
                      "text": "Flex Tower, 7-7-4 Midori-ku, Tokyo",
                      "wrap": true,
                      "color": "#666666",
                      "size": "sm",
                      "flex": 5
                    }
                  ]
                },
                {
                  "type": "box",
                  "layout": "baseline",
                  "spacing": "sm",
                  "contents": [
                    {
                      "type": "text",
                      "text": "Time",
                      "color": "#aaaaaa",
                      "size": "sm",
                      "flex": 1
                    },
                    {
                      "type": "text",
                      "text": "10:00 - 23:00",
                      "wrap": true,
                      "color": "#666666",
                      "size": "sm",
                      "flex": 5
                    }
                  ]
                }
              ]
            }
          ]
        },
        "footer": {
          "type": "box",
          "layout": "vertical",
          "spacing": "sm",
          "contents": [
            {
              "type": "button",
              "style": "link",
              "height": "sm",
              "action": {
                "type": "uri",
                "label": "CALL",
                "uri": "https://line.me/"
              }
            },
            {
              "type": "button",
              "style": "link",
              "height": "sm",
              "action": {
                "type": "uri",
                "label": "WEBSITE",
                "uri": "https://line.me/"
              }
            },
            {
              "type": "box",
              "layout": "vertical",
              "contents": [],
              "margin": "sm"
            }
          ],
          "flex": 0
        }
      },
      {
        "type": "bubble",
        "hero": {
          "type": "image",
          "url": "https://www.pet.gov.tw/upload/pic/1717147152900.png",
          "size": "full",
          "aspectRatio": "20:13",
          "aspectMode": "cover"
        },
        "body": {
          "type": "box",
          "layout": "vertical",
          "contents": [
            {
              "type": "text",
              "text": "混種犬  黑黃色 性別:母",
              "weight": "bold",
              "size": "xl"
            },
            {
              "type": "box",
              "layout": "baseline",
              "margin": "md",
              "contents": [
                {
                  "type": "text",
                  "text": "4.0",
                  "size": "sm",
                  "color": "#999999",
                  "margin": "md",
                  "flex": 0
                }
              ]
            },
            {
              "type": "box",
              "layout": "vertical",
              "margin": "lg",
              "spacing": "sm",
              "contents": [
                {
                  "type": "box",
                  "layout": "baseline",
                  "spacing": "sm",
                  "contents": [
                    {
                      "type": "text",
                      "text": "Place",
                      "color": "#aaaaaa",
                      "size": "sm",
                      "flex": 1
                    },
                    {
                      "type": "text",
                      "text": "Flex Tower, 7-7-4 Midori-ku, Tokyo",
                      "wrap": true,
                      "color": "#666666",
                      "size": "sm",
                      "flex": 5
                    }
                  ]
                },
                {
                  "type": "box",
                  "layout": "baseline",
                  "spacing": "sm",
                  "contents": [
                    {
                      "type": "text",
                      "text": "Time",
                      "color": "#aaaaaa",
                      "size": "sm",
                      "flex": 1
                    },
                    {
                      "type": "text",
                      "text": "10:00 - 23:00",
                      "wrap": true,
                      "color": "#666666",
                      "size": "sm",
                      "flex": 5
                    }
                  ]
                }
              ]
            }
          ]
        },
        "footer": {
          "type": "box",
          "layout": "vertical",
          "spacing": "sm",
          "contents": [
            {
              "type": "button",
              "style": "link",
              "height": "sm",
              "action": {
                "type": "uri",
                "label": "CALL",
                "uri": "https://line.me/"
              }
            },
            {
              "type": "button",
              "style": "link",
              "height": "sm",
              "action": {
                "type": "uri",
                "label": "WEBSITE",
                "uri": "https://line.me/"
              }
            },
            {
              "type": "box",
              "layout": "vertical",
              "contents": [],
              "margin": "sm"
            }
          ],
          "flex": 0
        }
      },
      {
        "type": "bubble",
        "hero": {
          "type": "image",
          "url": "",
          "size": "full",
          "aspectRatio": "20:13",
          "aspectMode": "cover"
        },
        "body": {
          "type": "box",
          "layout": "vertical",
          "contents": [
            {
              "type": "text",
              "text": "混種犬  黑色 性別:母",
              "weight": "bold",
              "size": "xl"
            },
            {
              "type": "box",
              "layout": "baseline",
              "margin": "md",
              "contents": [
                {
                  "type": "text",
                  "text": "4.0",
                  "size": "sm",
                  "color": "#999999",
                  "margin": "md",
                  "flex": 0
                }
              ]
            },
            {
              "type": "box",
              "layout": "vertical",
              "margin": "lg",
              "spacing": "sm",
              "contents": [
                {
                  "type": "box",
                  "layout": "baseline",
                  "spacing": "sm",
                  "contents": [
                    {
                      "type": "text",
                      "text": "Place",
                      "color": "#aaaaaa",
                      "size": "sm",
                      "flex": 1
                    },
                    {
                      "type": "text",
                      "text": "Flex Tower, 7-7-4 Midori-ku, Tokyo",
                      "wrap": true,
                      "color": "#666666",
                      "size": "sm",
                      "flex": 5
                    }
                  ]
                },
                {
                  "type": "box",
                  "layout": "baseline",
                  "spacing": "sm",
                  "contents": [
                    {
                      "type": "text",
                      "text": "Time",
                      "color": "#aaaaaa",
                      "size": "sm",
                      "flex": 1
                    },
                    {
                      "type": "text",
                      "text": "10:00 - 23:00",
                      "wrap": true,
                      "color": "#666666",
                      "size": "sm",
                      "flex": 5
                    }
                  ]
                }
              ]
            }
          ]
        },
        "footer": {
          "type": "box",
          "layout": "vertical",
          "spacing": "sm",
          "contents": [
            {
              "type": "button",
              "style": "link",
              "height": "sm",
              "action": {
                "type": "uri",
                "label": "CALL",
                "uri": "https://line.me/"
              }
            },
            {
              "type": "button",
              "style": "link",
              "height": "sm",
              "action": {
                "type": "uri",
                "label": "WEBSITE",
                "uri": "https://line.me/"
              }
            },
            {
              "type": "box",
              "layout": "vertical",
              "contents": [],
              "margin": "sm"
            }
          ],
          "flex": 0
        }
      },
      {
        "type": "bubble",
        "hero": {
          "type": "image",
          "url": "https://www.pet.gov.tw/upload/pic/1717146460026.png",
          "size": "full",
          "aspectRatio": "20:13",
          "aspectMode": "cover"
        },
        "body": {
          "type": "box",
          "layout": "vertical",
          "contents": [
            {
              "type": "text",
              "text": "混種犬  黑色 性別:母",
              "weight": "bold",
              "size": "xl"
            },
            {
              "type": "box",
              "layout": "baseline",
              "margin": "md",
              "contents": [
                {
                  "type": "text",
                  "text": "4.0",
                  "size": "sm",
                  "color": "#999999",
                  "margin": "md",
                  "flex": 0
                }
              ]
            },
            {
              "type": "box",
              "layout": "vertical",
              "margin": "lg",
              "spacing": "sm",
              "contents": [
                {
                  "type": "box",
                  "layout": "baseline",
                  "spacing": "sm",
                  "contents": [
                    {
                      "type": "text",
                      "text": "Place",
                      "color": "#aaaaaa",
                      "size": "sm",
                      "flex": 1
                    },
                    {
                      "type": "text",
                      "text": "Flex Tower, 7-7-4 Midori-ku, Tokyo",
                      "wrap": true,
                      "color": "#666666",
                      "size": "sm",
                      "flex": 5
                    }
                  ]
                },
                {
                  "type": "box",
                  "layout": "baseline",
                  "spacing": "sm",
                  "contents": [
                    {
                      "type": "text",
                      "text": "Time",
                      "color": "#aaaaaa",
                      "size": "sm",
                      "flex": 1
                    },
                    {
                      "type": "text",
                      "text": "10:00 - 23:00",
                      "wrap": true,
                      "color": "#666666",
                      "size": "sm",
                      "flex": 5
                    }
                  ]
                }
              ]
            }
          ]
        },
        "footer": {
          "type": "box",
          "layout": "vertical",
          "spacing": "sm",
          "contents": [
            {
              "type": "button",
              "style": "link",
              "height": "sm",
              "action": {
                "type": "uri",
                "label": "CALL",
                "uri": "https://line.me/"
              }
            },
            {
              "type": "button",
              "style": "link",
              "height": "sm",
              "action": {
                "type": "uri",
                "label": "WEBSITE",
                "uri": "https://line.me/"
              }
            },
            {
              "type": "box",
              "layout": "vertical",
              "contents": [],
              "margin": "sm"
            }
          ],
          "flex": 0
        }
      }
    ]
  }
}